setup.py
meshblu/__init__.py
meshblu/meshblu.py
meshblu.egg-info/PKG-INFO
meshblu.egg-info/SOURCES.txt
meshblu.egg-info/dependency_links.txt
meshblu.egg-info/requires.txt
meshblu.egg-info/top_level.txt