Metadata-Version: 1.1
Name: meshblu
Version: 0.1
Summary: Meshblu HTTP RESTful Python client
Home-page: https://github.com/drasko/meshblu-py
Author: Drasko DRASKOVIC
Author-email: drasko.draskovic@gmail.com
License: MIT
Download-URL: https://github.com/peterldowns/mypackage/tarball/0.1
Keywords: iot,meshblu,http
Platform: UNKNOWN
Classifier: License :: OSI Approved :: MIT License
Classifier: Programming Language :: Python
Classifier: Natural Language :: English
Classifier: Operating System :: OS Independent
Classifier: Development Status :: 4 - Beta
Classifier: Intended Audience :: Developers
Classifier: Topic :: Software Development :: Libraries
